[
  {
    "body": "Cinnamon twists",
    "created_utc": 1642930783,
    "has_media": false,
    "id": "t1_htv2hda",
    "permalink": "https://www.reddit.com/r/LivingMas/comments/sa6n7j/comment/htv2hda/",
    "score": 1,
    "status": "active",
    "subreddit": "LivingMas",
    "title": null,
    "type": "comment"
  },
  {
    "body": "Supreme nachos taco supreme?",
    "created_utc": 1643417881,
    "has_media": false,
    "id": "t1_huns448",
    "permalink": "https://www.reddit.com/r/LivingMas/comments/sf58j1/comment/huns448/",
    "score": 14,
    "status": "active",
    "subreddit": "LivingMas",
    "title": null,
    "type": "comment"
  },
  {
    "body": "Info has been leaked by other sources - it’s an Impossible Taco",
    "created_utc": 1644484446,
    "has_media": false,
    "id": "t1_hwchotp",
    "permalink": "https://www.reddit.com/r/LivingMas/comments/soch30/comment/hwchotp/",
    "score": 3,
    "status": "active",
    "subreddit": "LivingMas",
    "title": null,
    "type": "comment"
  },
  {
    "body": "To me it has a little too strong of a vinegar taste",
    "created_utc": 1645096139,
    "has_media": false,
    "id": "t1_hxam1ed",
    "permalink": "https://www.reddit.com/r/LivingMas/comments/stzzde/comment/hxam1ed/",
    "score": 1,
    "status": "active",
    "subreddit": "LivingMas",
    "title": null,
    "type": "comment"
  },
  {
    "body": "I appreciate the attempt and I’m sure it was delicious. But not gonna lie, the picture makes me want to 🤢",
    "created_utc": 1645523805,
    "has_media": false,
    "id": "t1_hxy4033",
    "permalink": "https://www.reddit.com/r/LivingMas/comments/sxfbkn/comment/hxy4033/",
    "score": 1,
    "status": "active",
    "subreddit": "LivingMas",
    "title": null,
    "type": "comment"
  },
  {
    "body": "Bruh",
    "created_utc": 1647149489,
    "has_media": false,
    "id": "t1_i0gl46r",
    "permalink": "https://www.reddit.com/r/LivingMas/comments/tcr8av/comment/i0gl46r/",
    "score": 3,
    "status": "active",
    "subreddit": "LivingMas",
    "title": null,
    "type": "comment"
  },
  {
    "body": "How does that boot taste? 👢",
    "created_utc": 1649328670,
    "has_media": false,
    "id": "t1_i3qwcjr",
    "permalink": "https://www.reddit.com/r/LivingMas/comments/ty2esb/comment/i3qwcjr/",
    "score": -15,
    "status": "active",
    "subreddit": "LivingMas",
    "title": null,
    "type": "comment"
  },
  {
    "body": "Yep, certainly nothing to do with corporate greed…",
    "created_utc": 1649842125,
    "has_media": false,
    "id": "t1_i4jm6p9",
    "permalink": "https://www.reddit.com/r/LivingMas/comments/u1gniv/comment/i4jm6p9/",
    "score": 3,
    "status": "active",
    "subreddit": "LivingMas",
    "title": null,
    "type": "comment"
  },
  {
    "body": "You likely have COVID",
    "created_utc": 1650454862,
    "has_media": false,
    "id": "t1_i5gw0gb",
    "permalink": "https://www.reddit.com/r/LivingMas/comments/u6v7py/comment/i5gw0gb/",
    "score": 1,
    "status": "active",
    "subreddit": "LivingMas",
    "title": null,
    "type": "comment"
  },
  {
    "body": "People who use obtuse acronyms for no reason, since it saves virtually no time in typing the message, drive me crazy.",
    "created_utc": 1651208894,
    "has_media": false,
    "id": "t1_i6mq15l",
    "permalink": "https://www.reddit.com/r/LivingMas/comments/ue6672/comment/i6mq15l/",
    "score": 14,
    "status": "active",
    "subreddit": "LivingMas",
    "title": null,
    "type": "comment"
  },
  {
    "body": "You seem fun",
    "created_utc": 1652876180,
    "has_media": false,
    "id": "t1_i92c5tm",
    "permalink": "https://www.reddit.com/r/LivingMas/comments/us5uri/comment/i92c5tm/",
    "score": 14,
    "status": "active",
    "subreddit": "LivingMas",
    "title": null,
    "type": "comment"
  },
  {
    "body": "It is the best fast food item there is.",
    "created_utc": 1652949309,
    "has_media": false,
    "id": "t1_i96hhpc",
    "permalink": "https://www.reddit.com/r/LivingMas/comments/usl0qg/comment/i96hhpc/",
    "score": 2,
    "status": "active",
    "subreddit": "LivingMas",
    "title": null,
    "type": "comment"
  },
  {
    "body": "2 Mexican pizzas and a half dozen hard shell tacos was my go to lunch for years. I’m hyped",
    "created_utc": 1653050100,
    "has_media": false,
    "id": "t1_i9bkrhi",
    "permalink": "https://www.reddit.com/r/LivingMas/comments/ut70md/comment/i9bkrhi/",
    "score": 5,
    "status": "active",
    "subreddit": "LivingMas",
    "title": null,
    "type": "comment"
  },
  {
    "body": "It looks like someone sat on it….",
    "created_utc": 1653533908,
    "has_media": false,
    "id": "t1_ia0r9dx",
    "permalink": "https://www.reddit.com/r/LivingMas/comments/uxxsd0/comment/ia0r9dx/",
    "score": 2,
    "status": "active",
    "subreddit": "LivingMas",
    "title": null,
    "type": "comment"
  },
  {
    "body": "Ok boomer",
    "created_utc": 1654431454,
    "has_media": false,
    "id": "t1_ib8uay1",
    "permalink": "https://www.reddit.com/r/LivingMas/comments/v4f2ti/comment/ib8uay1/",
    "score": 6,
    "status": "active",
    "subreddit": "LivingMas",
    "title": null,
    "type": "comment"
  },
  {
    "body": "Anyone else think this is one of the best breakfast items available? I get one nearly every day; add extra seasoned ground beef; extra creamy jalapeño sauce; and add sour cream. It is the perfect breakfast. Sometimes if I’m extra hungry I’ll get two. Like today 😊",
    "created_utc": 1657772194,
    "has_media": false,
    "id": "t3_vymum9",
    "permalink": "https://www.reddit.com/r/LivingMas/comments/vymum9/shoutout_to_the_breakfast_crunchwrap/",
    "score": 1,
    "status": "removed_by_mod",
    "subreddit": "LivingMas",
    "title": "Shoutout to the Breakfast Crunchwrap",
    "type": "submission"
  },
  {
    "body": "Breakfast crunchwraps are truly incredible. Pro tip: ALWAYS ask for extra creamy jalapeño sauce.",
    "created_utc": 1658306430,
    "has_media": false,
    "id": "t1_igw60bv",
    "permalink": "https://www.reddit.com/r/LivingMas/comments/w17cty/comment/igw60bv/",
    "score": 2,
    "status": "active",
    "subreddit": "LivingMas",
    "title": null,
    "type": "comment"
  },
  {
    "body": "I love the ad and it made me go out and get 2 Mexican pizzas, a grilled cheese burrito, and a cheesy Gordita crunch for dinner. Wish I had gotten maybe one more burrito or taco to fill me up but it is what it is",
    "created_utc": 1665462857,
    "has_media": false,
    "id": "t1_iruqcd1",
    "permalink": "https://www.reddit.com/r/LivingMas/comments/y0xxx1/comment/iruqcd1/",
    "score": -29,
    "status": "active",
    "subreddit": "LivingMas",
    "title": null,
    "type": "comment"
  },
  {
    "body": "Except for the prices, what’s wrong with chipotle? Clean ingredients and relatively healthy for what it is… it’s definitely a big step up from TB",
    "created_utc": 1665550865,
    "has_media": false,
    "id": "t1_irzi6de",
    "permalink": "https://www.reddit.com/r/LivingMas/comments/y1ok3v/comment/irzi6de/",
    "score": -14,
    "status": "active",
    "subreddit": "LivingMas",
    "title": null,
    "type": "comment"
  },
  {
    "body": "I don’t like quesadilla. Not a fan of cheese especially melted. Also creamy jalapeño sauce is like the worst they have",
    "created_utc": 1665551272,
    "has_media": false,
    "id": "t1_irziser",
    "permalink": "https://www.reddit.com/r/LivingMas/comments/y0gh6w/comment/irziser/",
    "score": -1,
    "status": "active",
    "subreddit": "LivingMas",
    "title": null,
    "type": "comment"
  },
  {
    "body": "My first kiss was a beefy frito burrito. And there was a period of time in high school where I literally ate 3 of these every day for months. When I went to college I broke that streak but it has a place in my heart always",
    "created_utc": 1668228132,
    "has_media": false,
    "id": "t1_iw1dr0h",
    "permalink": "https://www.reddit.com/r/LivingMas/comments/yrp7tz/comment/iw1dr0h/",
    "score": 1,
    "status": "active",
    "subreddit": "LivingMas",
    "title": null,
    "type": "comment"
  }
]
